rarbgcli/__init__.py
rarbgcli/download_tesseract.py
rarbgcli/get_chrome_driver.py
rarbgcli/rarbgcli.py
rarbgcli-0.0.24.dist-info/METADATA
rarbgcli-0.0.24.dist-info/WHEEL
rarbgcli-0.0.24.dist-info/entry_points.txt
rarbgcli-0.0.24.dist-info/top_level.txt
rarbgcli-0.0.24.dist-info/RECORD
