Metadata-Version: 2.1
Name: rarbgcli
Version: 0.0.24
Summary: Command line interface for rarbg.to
Home-page: https://github.com/FarisHijazi/rarbgcli
Author: Faris Hijazi
Author-email: theefaris@gmail.com
Keywords: rarbg torrent rarbgcli rarbgapi cli api scraper rarbg-cli rarbg-api rarbg-scraper
Requires-Python: >=3.6
Requires-Dist: asyncio
Requires-Dist: beautifulsoup4 (==4.11.1)
Requires-Dist: Pillow (==9.2.0)
Requires-Dist: prompt-toolkit (==3.0.20)
Requires-Dist: pytesseract (==0.3.9)
Requires-Dist: questionary (==1.10.0)
Requires-Dist: requests (==2.27.1)
Requires-Dist: selenium (==3.141.0)
Requires-Dist: tqdm
Requires-Dist: webdriver-manager (==3.8.3)
Requires-Dist: wget (==3.2)
